{"is_source_file": true, "file_id": 19, "git_revision": "", "state": 1, "description": "", "external_files": [], "external_methods": [], "published": [], "classes": [], "methods": [], "calls": [], "search-terms": [], "ctags": [{"_type": "tag", "name": "TodoList", "path": "/tmp/kavia/workspace/code-generation/simple-to-do-list-261-270/frontend_react/src/components/TodoList.js", "pattern": "/^export default function TodoList({ todos, onToggle, onDelete }) {$/", "language": "JavaScript", "kind": "function", "signature": "({ todos, onToggle, onDelete })"}], "format": "JavaScript", "hash": "d0575e128a16fa50c2ee7e341bd9459a", "format-version": 4, "code-base-name": "frontend_react", "filename": "frontend_react/src/components/TodoList.js", "knowledge_revision": 37}